{
  "resolvedId": "C:/webdev/Tutorials/nuxt-blog/components/Bounded.vue?vue&type=script&setup=true&lang.ts",
  "transforms": [
    {
      "name": "vite:vue",
      "result": "import { defineComponent as _defineComponent } from 'vue'\nimport { resolveDynamicComponent as _resolveDynamicComponent, withCtx as _withCtx, renderSlot as _renderSlot, createVNode as _createVNode, mergeProps as _mergeProps } from \"vue\"\nimport { ssrRenderSlot as _ssrRenderSlot, ssrRenderClass as _ssrRenderClass, ssrRenderVNode as _ssrRenderVNode } from \"vue/server-renderer\"\n\n\nexport default /*#__PURE__*/_defineComponent({\n  __name: 'Bounded',\n  __ssrInlineRender: true,\n  props: {\n  as: {\n    type: [String, Object],\n    default: 'div'\n  },\n  size: {\n    type: String,\n    default: 'base'\n  }\n},\n  setup(__props) {\n\n\n\nreturn (_ctx: any,_push: any,_parent: any,_attrs: any) => {\n  _ssrRenderVNode(_push, _createVNode(_resolveDynamicComponent(__props.as), _mergeProps({ class: \"px-4 py-8 md:py-10 md:px-6 lg:py-12\" }, _attrs), {\n    default: _withCtx((_, _push, _parent, _scopeId) => {\n      if (_push) {\n        _push(`<div class=\"${\n          _ssrRenderClass([{\n        'max-w-xl': __props.size === 'small',\n        'max-w-3xl': __props.size === 'base',\n        'max-w-4xl': __props.size === 'wide',\n        'max-w-6xl': __props.size === 'widest'\n      }, \"mx-auto w-full\"])\n        }\"${\n          _scopeId\n        }>`)\n        _ssrRenderSlot(_ctx.$slots, \"default\", {}, null, _push, _parent, _scopeId)\n        _push(`</div>`)\n      } else {\n        return [\n          _createVNode(\"div\", {\n            class: [\"mx-auto w-full\", {\n        'max-w-xl': __props.size === 'small',\n        'max-w-3xl': __props.size === 'base',\n        'max-w-4xl': __props.size === 'wide',\n        'max-w-6xl': __props.size === 'widest'\n      }]\n          }, [\n            _renderSlot(_ctx.$slots, \"default\")\n          ], 2)\n        ]\n      }\n    }),\n    _: 3\n  }), _parent)\n}\n}\n\n})",
      "start": 1720103997919,
      "end": 1720103997919,
      "sourcemaps": {
        "version": 3,
        "sources": [
          "C:/webdev/Tutorials/nuxt-blog/components/Bounded.vue"
        ],
        "sourcesContent": [
          "<script setup lang=\"ts\">\ndefineProps({\n  as: {\n    type: [String, Object],\n    default: 'div'\n  },\n  size: {\n    type: String,\n    default: 'base'\n  }\n})\n</script>\n\n<template>\n  <Component\n    :is=\"as\"\n    class=\"px-4 py-8 md:py-10 md:px-6 lg:py-12\"\n  >\n    <div\n      class=\"mx-auto w-full\"\n      :class=\"{\n        'max-w-xl': size === 'small',\n        'max-w-3xl': size === 'base',\n        'max-w-4xl': size === 'wide',\n        'max-w-6xl': size === 'widest'\n      }\"\n    >\n      <slot />\n    </div>\n  </Component>\n</template>\n\n"
        ],
        "names": [],
        "mappings": ";;;;;;;;;;;;;;;;;;;AAAwB;AAUtB;;;;;;;;;;;;;;;;;;;;;;;;;;;;;;;;;;;;;;"
      }
    },
    {
      "name": "nuxt:layer-aliasing",
      "start": 1720103997919,
      "end": 1720103997919,
      "order": "pre"
    },
    {
      "name": "nuxt:layer-aliasing",
      "start": 1720103997919,
      "end": 1720103997919,
      "order": "pre"
    },
    {
      "name": "nuxt:server-devonly:transform",
      "start": 1720103997919,
      "end": 1720103997919,
      "order": "pre"
    },
    {
      "name": "nuxt:server-devonly:transform",
      "start": 1720103997919,
      "end": 1720103997919,
      "order": "pre"
    },
    {
      "name": "nuxt:client-fallback-auto-id",
      "start": 1720103997919,
      "end": 1720103997919,
      "order": "pre"
    },
    {
      "name": "server-only-component-transform",
      "start": 1720103997919,
      "end": 1720103997919,
      "order": "pre"
    },
    {
      "name": "vite:css",
      "start": 1720103997919,
      "end": 1720103997919,
      "order": "normal"
    },
    {
      "name": "vite:esbuild",
      "result": "import { defineComponent as _defineComponent } from \"vue\";\nimport { resolveDynamicComponent as _resolveDynamicComponent, withCtx as _withCtx, renderSlot as _renderSlot, createVNode as _createVNode, mergeProps as _mergeProps } from \"vue\";\nimport { ssrRenderSlot as _ssrRenderSlot, ssrRenderClass as _ssrRenderClass, ssrRenderVNode as _ssrRenderVNode } from \"vue/server-renderer\";\nexport default /* @__PURE__ */ _defineComponent({\n  __name: \"Bounded\",\n  __ssrInlineRender: true,\n  props: {\n    as: {\n      type: [String, Object],\n      default: \"div\"\n    },\n    size: {\n      type: String,\n      default: \"base\"\n    }\n  },\n  setup(__props) {\n    return (_ctx, _push, _parent, _attrs) => {\n      _ssrRenderVNode(_push, _createVNode(_resolveDynamicComponent(__props.as), _mergeProps({ class: \"px-4 py-8 md:py-10 md:px-6 lg:py-12\" }, _attrs), {\n        default: _withCtx((_, _push2, _parent2, _scopeId) => {\n          if (_push2) {\n            _push2(`<div class=\"${_ssrRenderClass([{\n              \"max-w-xl\": __props.size === \"small\",\n              \"max-w-3xl\": __props.size === \"base\",\n              \"max-w-4xl\": __props.size === \"wide\",\n              \"max-w-6xl\": __props.size === \"widest\"\n            }, \"mx-auto w-full\"])}\"${_scopeId}>`);\n            _ssrRenderSlot(_ctx.$slots, \"default\", {}, null, _push2, _parent2, _scopeId);\n            _push2(`</div>`);\n          } else {\n            return [\n              _createVNode(\"div\", {\n                class: [\"mx-auto w-full\", {\n                  \"max-w-xl\": __props.size === \"small\",\n                  \"max-w-3xl\": __props.size === \"base\",\n                  \"max-w-4xl\": __props.size === \"wide\",\n                  \"max-w-6xl\": __props.size === \"widest\"\n                }]\n              }, [\n                _renderSlot(_ctx.$slots, \"default\")\n              ], 2)\n            ];\n          }\n        }),\n        _: 3\n      }), _parent);\n    };\n  }\n});\n",
      "start": 1720103997919,
      "end": 1720103997927,
      "order": "normal",
      "sourcemaps": {
        "version": 3,
        "sources": [
          "C:/webdev/Tutorials/nuxt-blog/components/Bounded.vue?vue&type=script&setup=true&lang.ts"
        ],
        "sourcesContent": [
          "import { defineComponent as _defineComponent } from 'vue'\nimport { resolveDynamicComponent as _resolveDynamicComponent, withCtx as _withCtx, renderSlot as _renderSlot, createVNode as _createVNode, mergeProps as _mergeProps } from \"vue\"\nimport { ssrRenderSlot as _ssrRenderSlot, ssrRenderClass as _ssrRenderClass, ssrRenderVNode as _ssrRenderVNode } from \"vue/server-renderer\"\n\n\nexport default /*#__PURE__*/_defineComponent({\n  __name: 'Bounded',\n  __ssrInlineRender: true,\n  props: {\n  as: {\n    type: [String, Object],\n    default: 'div'\n  },\n  size: {\n    type: String,\n    default: 'base'\n  }\n},\n  setup(__props) {\n\n\n\nreturn (_ctx: any,_push: any,_parent: any,_attrs: any) => {\n  _ssrRenderVNode(_push, _createVNode(_resolveDynamicComponent(__props.as), _mergeProps({ class: \"px-4 py-8 md:py-10 md:px-6 lg:py-12\" }, _attrs), {\n    default: _withCtx((_, _push, _parent, _scopeId) => {\n      if (_push) {\n        _push(`<div class=\"${\n          _ssrRenderClass([{\n        'max-w-xl': __props.size === 'small',\n        'max-w-3xl': __props.size === 'base',\n        'max-w-4xl': __props.size === 'wide',\n        'max-w-6xl': __props.size === 'widest'\n      }, \"mx-auto w-full\"])\n        }\"${\n          _scopeId\n        }>`)\n        _ssrRenderSlot(_ctx.$slots, \"default\", {}, null, _push, _parent, _scopeId)\n        _push(`</div>`)\n      } else {\n        return [\n          _createVNode(\"div\", {\n            class: [\"mx-auto w-full\", {\n        'max-w-xl': __props.size === 'small',\n        'max-w-3xl': __props.size === 'base',\n        'max-w-4xl': __props.size === 'wide',\n        'max-w-6xl': __props.size === 'widest'\n      }]\n          }, [\n            _renderSlot(_ctx.$slots, \"default\")\n          ], 2)\n        ]\n      }\n    }),\n    _: 3\n  }), _parent)\n}\n}\n\n})"
        ],
        "mappings": "AAAA,SAAS,mBAAmB,wBAAwB;AACpD,SAAS,2BAA2B,0BAA0B,WAAW,UAAU,cAAc,aAAa,eAAe,cAAc,cAAc,mBAAmB;AAC5K,SAAS,iBAAiB,gBAAgB,kBAAkB,iBAAiB,kBAAkB,uBAAuB;AAGtH,eAA4B,iCAAiB;AAAA,EAC3C,QAAQ;AAAA,EACR,mBAAmB;AAAA,EACnB,OAAO;AAAA,IACP,IAAI;AAAA,MACF,MAAM,CAAC,QAAQ,MAAM;AAAA,MACrB,SAAS;AAAA,IACX;AAAA,IACA,MAAM;AAAA,MACJ,MAAM;AAAA,MACN,SAAS;AAAA,IACX;AAAA,EACF;AAAA,EACE,MAAM,SAAS;AAIjB,WAAO,CAAC,MAAU,OAAW,SAAa,WAAgB;AACxD,sBAAgB,OAAO,aAAa,yBAAyB,QAAQ,EAAE,GAAG,YAAY,EAAE,OAAO,sCAAsC,GAAG,MAAM,GAAG;AAAA,QAC/I,SAAS,SAAS,CAAC,GAAGA,QAAOC,UAAS,aAAa;AACjD,cAAID,QAAO;AACT,YAAAA,OAAM,eACJ,gBAAgB,CAAC;AAAA,cACnB,YAAY,QAAQ,SAAS;AAAA,cAC7B,aAAa,QAAQ,SAAS;AAAA,cAC9B,aAAa,QAAQ,SAAS;AAAA,cAC9B,aAAa,QAAQ,SAAS;AAAA,YAChC,GAAG,gBAAgB,CAAC,CAClB,IACE,QACF,GAAG;AACH,2BAAe,KAAK,QAAQ,WAAW,CAAC,GAAG,MAAMA,QAAOC,UAAS,QAAQ;AACzE,YAAAD,OAAM,QAAQ;AAAA,UAChB,OAAO;AACL,mBAAO;AAAA,cACL,aAAa,OAAO;AAAA,gBAClB,OAAO,CAAC,kBAAkB;AAAA,kBAC9B,YAAY,QAAQ,SAAS;AAAA,kBAC7B,aAAa,QAAQ,SAAS;AAAA,kBAC9B,aAAa,QAAQ,SAAS;AAAA,kBAC9B,aAAa,QAAQ,SAAS;AAAA,gBAChC,CAAC;AAAA,cACG,GAAG;AAAA,gBACD,YAAY,KAAK,QAAQ,SAAS;AAAA,cACpC,GAAG,CAAC;AAAA,YACN;AAAA,UACF;AAAA,QACF,CAAC;AAAA,QACD,GAAG;AAAA,MACL,CAAC,GAAG,OAAO;AAAA,IACb;AAAA,EACA;AAEA,CAAC;",
        "names": [
          "_push",
          "_parent"
        ]
      }
    },
    {
      "name": "vite:json",
      "start": 1720103997927,
      "end": 1720103997927,
      "order": "normal"
    },
    {
      "name": "vite:worker",
      "start": 1720103997927,
      "end": 1720103997927,
      "order": "normal"
    },
    {
      "name": "vite:vue",
      "start": 1720103997927,
      "end": 1720103997927,
      "order": "normal"
    },
    {
      "name": "vite:vue-jsx",
      "start": 1720103997927,
      "end": 1720103997927,
      "order": "normal"
    },
    {
      "name": "replace",
      "start": 1720103997927,
      "end": 1720103997927,
      "order": "normal"
    },
    {
      "name": "replace",
      "start": 1720103997927,
      "end": 1720103997927,
      "order": "normal"
    },
    {
      "name": "nuxt:remove-plugin-metadata",
      "start": 1720103997927,
      "end": 1720103997927,
      "order": "normal"
    },
    {
      "name": "nuxt:remove-plugin-metadata",
      "start": 1720103997927,
      "end": 1720103997927,
      "order": "normal"
    },
    {
      "name": "nuxt:components:imports",
      "start": 1720103997927,
      "end": 1720103997927,
      "order": "normal"
    },
    {
      "name": "replace",
      "start": 1720103997927,
      "end": 1720103997927,
      "order": "normal"
    },
    {
      "name": "ssr-styles",
      "start": 1720103997927,
      "end": 1720103997928,
      "order": "normal"
    },
    {
      "name": "vite:define",
      "start": 1720103997928,
      "end": 1720103997928,
      "order": "normal"
    },
    {
      "name": "vite:css-post",
      "start": 1720103997928,
      "end": 1720103997928,
      "order": "normal"
    },
    {
      "name": "vite:build-html",
      "start": 1720103997928,
      "end": 1720103997928,
      "order": "normal"
    },
    {
      "name": "vite:worker-import-meta-url",
      "start": 1720103997928,
      "end": 1720103997928,
      "order": "normal"
    },
    {
      "name": "vite:asset-import-meta-url",
      "start": 1720103997928,
      "end": 1720103997928,
      "order": "normal"
    },
    {
      "name": "commonjs",
      "start": 1720103997928,
      "end": 1720103997928,
      "order": "normal"
    },
    {
      "name": "vite:dynamic-import-vars",
      "start": 1720103997928,
      "end": 1720103997928,
      "order": "normal"
    },
    {
      "name": "vite:import-glob",
      "start": 1720103997928,
      "end": 1720103997928,
      "order": "normal"
    },
    {
      "name": "nuxt:composable-keys",
      "start": 1720103997928,
      "end": 1720103997928,
      "order": "post"
    },
    {
      "name": "nuxt:composable-keys",
      "start": 1720103997928,
      "end": 1720103997928,
      "order": "post"
    },
    {
      "name": "nuxt:imports-transform",
      "start": 1720103997928,
      "end": 1720103997929,
      "order": "post"
    },
    {
      "name": "nuxt:imports-transform",
      "start": 1720103997928,
      "end": 1720103997929,
      "order": "post"
    },
    {
      "name": "unctx:transform",
      "start": 1720103997929,
      "end": 1720103997929,
      "order": "post"
    },
    {
      "name": "unctx:transform",
      "start": 1720103997929,
      "end": 1720103997929,
      "order": "post"
    },
    {
      "name": "nuxt:pages-macros-transform",
      "start": 1720103997929,
      "end": 1720103997929,
      "order": "post"
    },
    {
      "name": "nuxt:pages-macros-transform",
      "start": 1720103997929,
      "end": 1720103997929,
      "order": "post"
    },
    {
      "name": "nuxt:tree-shake-template",
      "start": 1720103997929,
      "end": 1720103997929,
      "order": "post"
    },
    {
      "name": "nuxt:components-loader",
      "start": 1720103997929,
      "end": 1720103997929,
      "order": "post"
    },
    {
      "name": "nuxt:tree-shake-composables:transform",
      "start": 1720103997929,
      "end": 1720103997929,
      "order": "post"
    },
    {
      "name": "vite:build-import-analysis",
      "start": 1720103997929,
      "end": 1720103997929,
      "order": "normal"
    },
    {
      "name": "vite:reporter",
      "start": 1720103997929,
      "end": 1720103997929,
      "order": "normal"
    }
  ]
}
