{
  "resolvedId": "C:/webdev/Tutorials/nuxt-blog/components/Field.vue?vue&type=script&setup=true&lang.ts",
  "transforms": [
    {
      "name": "vite:vue",
      "result": "import { defineComponent as _defineComponent } from 'vue'\nimport { ssrRenderSlot as _ssrRenderSlot, ssrRenderAttrs as _ssrRenderAttrs, ssrInterpolate as _ssrInterpolate } from \"vue/server-renderer\"\n\n\nexport default /*#__PURE__*/_defineComponent({\n  __name: 'Field',\n  __ssrInlineRender: true,\n  props: {\r\n  label: {\r\n    type: String,\r\n    required: true\r\n  }\r\n},\n  setup(__props) {\n\r\n\r\n\nreturn (_ctx: any,_push: any,_parent: any,_attrs: any) => {\n  _push(`<label${\n    _ssrRenderAttrs(_attrs)\n  }><span class=\"text-sm text-slate-500\">${\n    _ssrInterpolate(__props.label)\n  }</span>`)\n  _ssrRenderSlot(_ctx.$slots, \"default\", {}, null, _push, _parent)\n  _push(`</label>`)\n}\n}\n\n})",
      "start": 1720177713875,
      "end": 1720177713875,
      "sourcemaps": {
        "version": 3,
        "sources": [
          "C:/webdev/Tutorials/nuxt-blog/components/Field.vue"
        ],
        "sourcesContent": [
          "<script setup lang=\"ts\">\r\ndefineProps({\r\n  label: {\r\n    type: String,\r\n    required: true\r\n  }\r\n})\r\n</script>\r\n\r\n<template>\r\n  <label>\r\n    <span class=\"text-sm text-slate-500\">{{ label }}</span>\r\n    <slot />\r\n  </label>\r\n</template>\r\n\r\n"
        ],
        "names": [],
        "mappings": ";;;;;;;;;;;;;;AAAwB,CAAC;AAMvB,CAAC;;;;;;;;;;;;;"
      }
    },
    {
      "name": "nuxt:layer-aliasing",
      "start": 1720177713875,
      "end": 1720177713875,
      "order": "pre"
    },
    {
      "name": "nuxt:layer-aliasing",
      "start": 1720177713875,
      "end": 1720177713875,
      "order": "pre"
    },
    {
      "name": "nuxt:server-devonly:transform",
      "start": 1720177713875,
      "end": 1720177713875,
      "order": "pre"
    },
    {
      "name": "nuxt:server-devonly:transform",
      "start": 1720177713875,
      "end": 1720177713875,
      "order": "pre"
    },
    {
      "name": "nuxt:client-fallback-auto-id",
      "start": 1720177713875,
      "end": 1720177713875,
      "order": "pre"
    },
    {
      "name": "server-only-component-transform",
      "start": 1720177713875,
      "end": 1720177713875,
      "order": "pre"
    },
    {
      "name": "vite:css",
      "start": 1720177713875,
      "end": 1720177713875,
      "order": "normal"
    },
    {
      "name": "vite:esbuild",
      "result": "import { defineComponent as _defineComponent } from \"vue\";\nimport { ssrRenderSlot as _ssrRenderSlot, ssrRenderAttrs as _ssrRenderAttrs, ssrInterpolate as _ssrInterpolate } from \"vue/server-renderer\";\nexport default /* @__PURE__ */ _defineComponent({\n  __name: \"Field\",\n  __ssrInlineRender: true,\n  props: {\n    label: {\n      type: String,\n      required: true\n    }\n  },\n  setup(__props) {\n    return (_ctx, _push, _parent, _attrs) => {\n      _push(`<label${_ssrRenderAttrs(_attrs)}><span class=\"text-sm text-slate-500\">${_ssrInterpolate(__props.label)}</span>`);\n      _ssrRenderSlot(_ctx.$slots, \"default\", {}, null, _push, _parent);\n      _push(`</label>`);\n    };\n  }\n});\n",
      "start": 1720177713875,
      "end": 1720177713882,
      "order": "normal",
      "sourcemaps": {
        "version": 3,
        "sources": [
          "C:/webdev/Tutorials/nuxt-blog/components/Field.vue?vue&type=script&setup=true&lang.ts"
        ],
        "sourcesContent": [
          "import { defineComponent as _defineComponent } from 'vue'\nimport { ssrRenderSlot as _ssrRenderSlot, ssrRenderAttrs as _ssrRenderAttrs, ssrInterpolate as _ssrInterpolate } from \"vue/server-renderer\"\n\n\nexport default /*#__PURE__*/_defineComponent({\n  __name: 'Field',\n  __ssrInlineRender: true,\n  props: {\r\n  label: {\r\n    type: String,\r\n    required: true\r\n  }\r\n},\n  setup(__props) {\n\r\n\r\n\nreturn (_ctx: any,_push: any,_parent: any,_attrs: any) => {\n  _push(`<label${\n    _ssrRenderAttrs(_attrs)\n  }><span class=\"text-sm text-slate-500\">${\n    _ssrInterpolate(__props.label)\n  }</span>`)\n  _ssrRenderSlot(_ctx.$slots, \"default\", {}, null, _push, _parent)\n  _push(`</label>`)\n}\n}\n\n})"
        ],
        "mappings": "AAAA,SAAS,mBAAmB,wBAAwB;AACpD,SAAS,iBAAiB,gBAAgB,kBAAkB,iBAAiB,kBAAkB,uBAAuB;AAGtH,eAA4B,iCAAiB;AAAA,EAC3C,QAAQ;AAAA,EACR,mBAAmB;AAAA,EACnB,OAAO;AAAA,IACP,OAAO;AAAA,MACL,MAAM;AAAA,MACN,UAAU;AAAA,IACZ;AAAA,EACF;AAAA,EACE,MAAM,SAAS;AAIjB,WAAO,CAAC,MAAU,OAAW,SAAa,WAAgB;AACxD,YAAM,SACJ,gBAAgB,MAAM,CACxB,yCACE,gBAAgB,QAAQ,KAAK,CAC/B,SAAS;AACT,qBAAe,KAAK,QAAQ,WAAW,CAAC,GAAG,MAAM,OAAO,OAAO;AAC/D,YAAM,UAAU;AAAA,IAClB;AAAA,EACA;AAEA,CAAC;",
        "names": []
      }
    },
    {
      "name": "vite:json",
      "start": 1720177713882,
      "end": 1720177713882,
      "order": "normal"
    },
    {
      "name": "vite:worker",
      "start": 1720177713882,
      "end": 1720177713882,
      "order": "normal"
    },
    {
      "name": "vite:vue",
      "start": 1720177713882,
      "end": 1720177713882,
      "order": "normal"
    },
    {
      "name": "vite:vue-jsx",
      "start": 1720177713882,
      "end": 1720177713882,
      "order": "normal"
    },
    {
      "name": "replace",
      "start": 1720177713882,
      "end": 1720177713882,
      "order": "normal"
    },
    {
      "name": "replace",
      "start": 1720177713882,
      "end": 1720177713882,
      "order": "normal"
    },
    {
      "name": "nuxt:remove-plugin-metadata",
      "start": 1720177713882,
      "end": 1720177713882,
      "order": "normal"
    },
    {
      "name": "nuxt:remove-plugin-metadata",
      "start": 1720177713882,
      "end": 1720177713882,
      "order": "normal"
    },
    {
      "name": "nuxt:components:imports",
      "start": 1720177713882,
      "end": 1720177713882,
      "order": "normal"
    },
    {
      "name": "replace",
      "start": 1720177713882,
      "end": 1720177713882,
      "order": "normal"
    },
    {
      "name": "ssr-styles",
      "start": 1720177713882,
      "end": 1720177713883,
      "order": "normal"
    },
    {
      "name": "vite:define",
      "start": 1720177713883,
      "end": 1720177713883,
      "order": "normal"
    },
    {
      "name": "vite:css-post",
      "start": 1720177713883,
      "end": 1720177713883,
      "order": "normal"
    },
    {
      "name": "vite:build-html",
      "start": 1720177713883,
      "end": 1720177713883,
      "order": "normal"
    },
    {
      "name": "vite:worker-import-meta-url",
      "start": 1720177713883,
      "end": 1720177713883,
      "order": "normal"
    },
    {
      "name": "vite:asset-import-meta-url",
      "start": 1720177713883,
      "end": 1720177713883,
      "order": "normal"
    },
    {
      "name": "commonjs",
      "start": 1720177713883,
      "end": 1720177713883,
      "order": "normal"
    },
    {
      "name": "vite:dynamic-import-vars",
      "start": 1720177713883,
      "end": 1720177713883,
      "order": "normal"
    },
    {
      "name": "vite:import-glob",
      "start": 1720177713883,
      "end": 1720177713883,
      "order": "normal"
    },
    {
      "name": "nuxt:composable-keys",
      "start": 1720177713883,
      "end": 1720177713883,
      "order": "post"
    },
    {
      "name": "nuxt:composable-keys",
      "start": 1720177713883,
      "end": 1720177713883,
      "order": "post"
    },
    {
      "name": "nuxt:imports-transform",
      "start": 1720177713883,
      "end": 1720177713884,
      "order": "post"
    },
    {
      "name": "nuxt:imports-transform",
      "start": 1720177713883,
      "end": 1720177713884,
      "order": "post"
    },
    {
      "name": "unctx:transform",
      "start": 1720177713884,
      "end": 1720177713884,
      "order": "post"
    },
    {
      "name": "unctx:transform",
      "start": 1720177713884,
      "end": 1720177713884,
      "order": "post"
    },
    {
      "name": "nuxt:pages-macros-transform",
      "start": 1720177713884,
      "end": 1720177713884,
      "order": "post"
    },
    {
      "name": "nuxt:pages-macros-transform",
      "start": 1720177713884,
      "end": 1720177713884,
      "order": "post"
    },
    {
      "name": "nuxt:tree-shake-template",
      "start": 1720177713884,
      "end": 1720177713884,
      "order": "post"
    },
    {
      "name": "nuxt:components-loader",
      "start": 1720177713884,
      "end": 1720177713884,
      "order": "post"
    },
    {
      "name": "nuxt:tree-shake-composables:transform",
      "start": 1720177713884,
      "end": 1720177713884,
      "order": "post"
    },
    {
      "name": "vite:build-import-analysis",
      "start": 1720177713884,
      "end": 1720177713884,
      "order": "normal"
    },
    {
      "name": "vite:reporter",
      "start": 1720177713884,
      "end": 1720177713884,
      "order": "normal"
    }
  ]
}
